{
  "zombie": {"name":"僵尸","category":"小怪","trait":"近战压迫","waves":[1,20],"hp":44,"speed":78,"damage":14,"xp":5,"radius":14,"color":"#7ccf68","behavior":"melee","desc":"最基础的近战敌人，移动慢但比较耐打，会持续向玩家逼近。","tip":"利用走位和范围武器边退边清，不要被数量包住。"},
  "speeder": {"name":"急行者","category":"小怪","trait":"高速突进","waves":[2,20],"hp":34,"speed":118,"damage":12,"xp":4,"radius":12,"color":"#ffd166","behavior":"speeder","desc":"会蓄力后突然加速冲脸，适合混在怪潮里打乱节奏。","tip":"看到它准备冲刺时横向拉开，不要直线后撤。"},
  "lancer": {"name":"突刺者","category":"小怪","trait":"直线穿刺","waves":[3,20],"hp":52,"speed":82,"damage":18,"xp":7,"radius":15,"color":"#ff9f6e","behavior":"lancer","desc":"会朝玩家方向猛冲，瞬时爆发比普通近战更高。","tip":"保持斜向移动，让它扑空后再回头输出。"},
  "wisp": {"name":"冰霜幽灵","category":"小怪","trait":"远程风筝","waves":[4,20],"hp":38,"speed":70,"damage":10,"xp":8,"radius":13,"color":"#9ff4ff","behavior":"ranged","desc":"会与玩家保持距离并持续发射弹幕。","tip":"优先处理，避免远程弹幕在场上越积越多。"},
  "slime_large": {"name":"大型史莱姆","category":"小怪","trait":"分裂压场","waves":[5,20],"hp":160,"speed":45,"damage":25,"xp":16,"radius":25,"color":"#77ff8a","behavior":"split_large","desc":"行动最慢，但生命和碰撞伤害最高，死亡后会分裂。","tip":"尽量在空旷区域击杀，避免被分裂体围住。"},
  "slime_medium": {"name":"中型史莱姆","category":"小怪","trait":"二段分裂","waves":[5,20],"hp":68,"speed":82,"damage":14,"xp":7,"radius":17,"color":"#66d96d","behavior":"split_medium","desc":"由大型史莱姆分裂而来，速度更快，还会继续分裂。","tip":"保持移动，把它们引成一串后集中清理。"},
  "slime_small": {"name":"小型史莱姆","category":"小怪","trait":"高速骚扰","waves":[5,20],"hp":24,"speed":128,"damage":8,"xp":3,"radius":10,"color":"#b6ff99","behavior":"melee","desc":"史莱姆家族里速度最快，数量多时压迫感很强。","tip":"不要贪金币，优先清小体型单位避免被追上。"},
  "blackhole_mage": {"name":"黑洞法师","category":"小怪","trait":"区域控制","waves":[7,20],"hp":62,"speed":56,"damage":10,"xp":12,"radius":15,"color":"#8d6bff","behavior":"hazard_mage","desc":"会在玩家附近召唤黑洞，制造牵引和持续伤害区域。","tip":"看到黑洞立刻离开边缘，别在黑洞与怪潮之间停留。"},
  "blink_skirmisher": {"name":"闪跃游斗者","category":"小怪","trait":"闪现切入","waves":[8,20],"hp":58,"speed":92,"damage":16,"xp":10,"radius":14,"color":"#ff65d8","behavior":"blink","desc":"会通过短距离闪现反复切入，近身节奏很灵活。","tip":"输出时多留位移空间，不要站在角落和边界附近。"},
  "embermine": {"name":"余烬地雷兽","category":"小怪","trait":"地雷封锁","waves":[8,20],"hp":55,"speed":72,"damage":16,"xp":9,"radius":14,"color":"#ff7a1a","behavior":"mine","desc":"喜欢逼近后布置火焰地雷，拖慢玩家的走位空间。","tip":"优先拉开并引爆它布下的危险区域。"},
  "siege_pylon": {"name":"攻城棱塔","category":"小怪","trait":"驻点火力","waves":[9,20],"hp":120,"speed":28,"damage":15,"xp":15,"radius":20,"color":"#42e8ff","behavior":"pylon","desc":"移动慢但射程远，会持续向玩家压制。","tip":"尽快贴近处理，拖得越久场面越乱。"},
  "razorbat": {"name":"刃翼蝠","category":"小怪","trait":"俯冲骚扰","waves":[9,20],"hp":36,"speed":150,"damage":13,"xp":8,"radius":12,"color":"#c7d2ff","behavior":"bat","desc":"会高速掠过玩家，穿插在怪群里进行骚扰。","tip":"利用范围和自动索敌武器优先打空中单位。"},
  "brood_seeder": {"name":"巢种播撒者","category":"小怪","trait":"召唤增殖","waves":[10,20],"hp":88,"speed":55,"damage":10,"xp":16,"radius":17,"color":"#a3e635","behavior":"summoner","desc":"会不断产出额外小怪，让战场人口迅速膨胀。","tip":"看到它优先集火，不然会把局面拖进刷怪雪崩。"},
  "line_raider": {"name":"裂空突袭者","category":"小怪","trait":"无敌穿场","waves":[11,20],"hp":90,"speed":170,"damage":24,"xp":18,"radius":14,"color":"#ffffff","behavior":"line_raider","desc":"会先用预警线锁定路线，再高速横穿整张地图。","tip":"看到预警通道就立刻离开，绝对不要和它抢线路。"},
  "shield_caster": {"name":"护盾施术者","category":"小怪","trait":"团队增益","waves":[11,20],"hp":72,"speed":52,"damage":7,"xp":14,"radius":15,"color":"#7dd3fc","behavior":"shield","desc":"不会直接进攻，但会给附近敌人套上大幅减伤护盾。","tip":"优先击杀它，否则周围怪物会变得很难处理。"},
  "wizard": {"name":"奥术巫师","category":"小怪","trait":"定点轰炸","waves":[12,20],"hp":64,"speed":50,"damage":16,"xp":14,"radius":15,"color":"#b48cff","behavior":"wizard","desc":"会隔着怪潮向玩家发射法术弹，是稳定的后排火力点。","tip":"靠机动走位躲弹，同时用穿透或追踪武器处理它。"},
  "exploder": {"name":"爆裂自毁者","category":"小怪","trait":"近身爆炸","waves":[12,20],"hp":38,"speed":104,"damage":32,"xp":9,"radius":13,"color":"#ff4d6d","behavior":"exploder","desc":"接近玩家后会自爆，伤害高但身板脆。","tip":"不要在怪群中心引爆它，尽量在边缘提前点掉。"},
  "tank": {"name":"重甲蛮牛","category":"小怪","trait":"重装推进","waves":[6,20],"hp":150,"speed":48,"damage":24,"xp":15,"radius":24,"color":"#b48cff","behavior":"melee","desc":"高生命高碰撞伤害，适合给其他远程怪创造输出空间。","tip":"用持续伤害和击退把它卡在怪潮外圈。"},
  "gunner": {"name":"几何枪手","category":"小怪","trait":"中程点射","waves":[13,20],"hp":70,"speed":62,"damage":15,"xp":13,"radius":15,"color":"#f3f7ff","behavior":"gunner","desc":"会边走边打，在中距离不断补枪。","tip":"斜向移动最容易躲掉它的直线弹道。"},
  "artillery": {"name":"炮击方碑","category":"小怪","trait":"抛射压制","waves":[14,20],"hp":95,"speed":34,"damage":18,"xp":18,"radius":18,"color":"#f97316","behavior":"artillery","desc":"擅长远距离抛射火力，会把危险点提前铺在前方。","tip":"别停在原地输出，持续移动能让它的大部分炮火落空。"},
  "elite_summoner": {"name":"精英·召魂统领","category":"精英","trait":"召唤核心","waves":[13,20],"hp":260,"speed":48,"damage":14,"xp":42,"radius":24,"color":"#84cc16","behavior":"summoner","elite":true,"desc":"强化版召唤单位，能稳定制造额外前排。","tip":"一旦出现就优先集火，避免它把战场重新堆满。"},
  "elite_berserker": {"name":"精英·狂怒战兽","category":"精英","trait":"半血狂暴","waves":[14,20],"hp":340,"speed":70,"damage":28,"xp":45,"radius":26,"color":"#ef4444","behavior":"berserker","elite":true,"desc":"高生命近战单位，半血后会进一步加速冲锋。","tip":"最好在安全距离把它一口气压死，别给它狂暴反扑机会。"},
  "elite_assassin": {"name":"精英·影刃刺客","category":"精英","trait":"瞬移追猎","waves":[15,20],"hp":210,"speed":115,"damage":30,"xp":48,"radius":19,"color":"#d946ef","behavior":"blink","elite":true,"desc":"会突然闪到玩家背后，擅长抓走位停顿。","tip":"保持连续移动，背后留足空间。"},
  "elite_sentinel": {"name":"精英·棱镜哨兵","category":"精英","trait":"弹幕炮台","waves":[16,20],"hp":300,"speed":36,"damage":22,"xp":52,"radius":23,"color":"#22d3ee","behavior":"pylon","elite":true,"desc":"火力更密集的远程精英，会持续制造大片危险区域。","tip":"拉远小怪后回头点杀，避免和其他远程怪叠弹幕。"},
  "elite_missile_sniper": {"name":"精英·导弹狙击者","category":"精英","trait":"跟踪爆破","waves":[17,20],"hp":260,"speed":44,"damage":26,"xp":55,"radius":22,"color":"#fb923c","behavior":"wizard","elite":true,"desc":"蓄力后发射跟踪导弹，爆炸后还会留下持续灼烧区域。","tip":"看见蓄力就提前拐弯，让导弹在安全位置炸开。"},
  "storm_tyrant": {"name":"风暴暴君","category":"Boss","trait":"多态弹幕","bossWave":5,"hp":2400,"speed":54,"damage":30,"xp":180,"radius":58,"color":"#42e8ff","behavior":"boss_storm","boss":true,"desc":"会在散射、环阵和冲锋之间切换，还会召唤帮手压场。","tip":"预留绕场空间，优先关注它当前切换到的攻击模式。"},
  "void_colossus": {"name":"虚空巨像","category":"Boss","trait":"重压控制","bossWave":10,"hp":4200,"speed":38,"damage":36,"xp":260,"radius":70,"color":"#8d6bff","behavior":"boss_void","boss":true,"desc":"兼具弹幕、引力和范围控制能力，是偏厚重的压制型 Boss。","tip":"不要在重力技能附近停留太久，绕大圈拉扯更安全。"},
  "geometric_devourer": {"name":"几何吞噬者","category":"Boss","trait":"长蛇追猎","bossWave":15,"hp":5600,"speed":62,"damage":40,"xp":320,"radius":64,"color":"#77ff8a","behavior":"boss_snake","boss":true,"desc":"多关节的蛇形 Boss，会巡航射击、突击冲锋并在二阶段加入传送与火球。","tip":"看准头部转向节奏，提前侧移，不要和它比直线奔跑。"},
  "dark_crystal_rift": {"name":"暗晶裂境主","category":"Boss","trait":"三阶暗晶","bossWave":20,"hp":7600,"speed":44,"damage":44,"xp":500,"radius":76,"color":"#ff4d6d","behavior":"boss_crystal","boss":true,"desc":"旋转八边形水晶领主，在暗晶散射、虚空刺穿、晶域封锁三种模式间循环切换。","tip":"三阶段裂变风暴需持续移动，不要停顿。"}
}
